{
    "Fira": {
        "branch": "master",
        "description": "Mozilla's new typeface, used in Firefox OS",
        "homepage": "mozilla.github.io/Fira",
        "owner": "mozilla",
        "repo": "Fira",
        "rev": "fd8c8c0a3d353cd99e8ca1662942d165e6961407",
        "sha256": "01cmam79kj0w2aw4a5hnh52d385fyn6li3apmxdsangcy99cx69m",
        "type": "tarball",
        "url": "https://github.com/mozilla/Fira/archive/fd8c8c0a3d353cd99e8ca1662942d165e6961407.tar.gz",
        "url_template": "https://github.com/<owner>/<repo>/archive/<rev>.tar.gz"
    },
    "minimal.css": {
        "branch": "master",
        "description": "An opinionated (currently naïve), inheritance focused alternative to CSS resets",
        "homepage": "https://lukebrooker.com/minimal.css",
        "owner": "lukebrooker",
        "repo": "minimal.css",
        "rev": "0e60c54e908328c8d6f9659b8dd1e549d3fdb28a",
        "sha256": "0xb4psqagkcmjymwk7wvf9injxq0c4xr3lxs59pniiavx6kxc1j9",
        "type": "tarball",
        "url": "https://github.com/lukebrooker/minimal.css/archive/0e60c54e908328c8d6f9659b8dd1e549d3fdb28a.tar.gz",
        "url_template": "https://github.com/<owner>/<repo>/archive/<rev>.tar.gz"
    },
    "nixpkgs": {
        "branch": "nixpkgs-unstable",
        "description": "DEPRECATED! This is an obsolete, read-only mirror of the NixOS/nixpkgs repository.",
        "homepage": "https://github.com/NixOS/nixpkgs",
        "owner": "NixOS",
        "repo": "nixpkgs-channels",
        "rev": "502845c3e31ef3de0e424f3fcb09217df2ce6df6",
        "sha256": "0fcqpsy6y7dgn0y0wgpa56gsg0b0p8avlpjrd79fp4mp9bl18nda",
        "type": "tarball",
        "url": "https://github.com/NixOS/nixpkgs-channels/archive/502845c3e31ef3de0e424f3fcb09217df2ce6df6.tar.gz",
        "url_template": "https://github.com/<owner>/<repo>/archive/<rev>.tar.gz"
    },
    "pandoc-lens": {
        "branch": "master",
        "description": "Lenses for the Pandoc AST",
        "homepage": null,
        "owner": "bradparker",
        "repo": "pandoc-lens",
        "rev": "320bba506305f16e581b8fb31c32d3233975c2fc",
        "sha256": "1xvj2i66w52bbm6rwrqvh7g0lfg9x8rdh9cljniifm4f89nzrjj7",
        "type": "tarball",
        "url": "https://github.com/bradparker/pandoc-lens/archive/320bba506305f16e581b8fb31c32d3233975c2fc.tar.gz",
        "url_template": "https://github.com/<owner>/<repo>/archive/<rev>.tar.gz"
    },
    "tachyons": {
        "branch": "master",
        "description": "Functional css for humans",
        "homepage": "https://tachyons.io",
        "owner": "tachyons-css",
        "repo": "tachyons",
        "rev": "79f4de4ea4b999200cfe0cf6c53738a18bc399c3",
        "sha256": "0nsj1cwarwn3flpz4jb1vs1dj3h489j7m303wyqj5057s7grz6ns",
        "type": "tarball",
        "url": "https://github.com/tachyons-css/tachyons/archive/79f4de4ea4b999200cfe0cf6c53738a18bc399c3.tar.gz",
        "url_template": "https://github.com/<owner>/<repo>/archive/<rev>.tar.gz"
    },
    "warp-systemd": {
        "branch": "master",
        "description": "Socket activation and other systemd integration for the Warp web server (WAI)",
        "homepage": null,
        "owner": "bradparker",
        "repo": "warp-systemd",
        "rev": "35cab9dd1114374f9297a27c6986792ccfec200c",
        "sha256": "00lc7zsr5kpgblb2nv2d10cw593i0r9mq0brzxbnrlhhawn7k8ga",
        "type": "tarball",
        "url": "https://github.com/bradparker/warp-systemd/archive/35cab9dd1114374f9297a27c6986792ccfec200c.tar.gz",
        "url_template": "https://github.com/<owner>/<repo>/archive/<rev>.tar.gz"
    }
}
